[
  {
    "_id": "6616cf9736f9ff8df06ff404",
    "index": 0,
    "guid": "30c92e66-1194-4d28-bd1b-e1fc4f491fef",
    "isActive": true,
    "balance": "$3,869.77",
    "picture": "http://placehold.it/32x32",
    "age": 32,
    "eyeColor": "brown",
    "name": "Moss Alston",
    "gender": "male",
    "company": "TERSANKI",
    "email": "mossalston@tersanki.com",
    "phone": "+1 (992) 569-3695",
    "address": "510 Flatlands Avenue, Twilight, Texas, 9823",
    "about": "Nisi est ex id tempor eu id Lorem cillum voluptate. Aliquip id sit tempor voluptate duis voluptate voluptate labore dolor mollit amet irure. Ad amet quis ex aute. Voluptate voluptate deserunt duis aliquip amet. Incididunt in dolore sint ea quis nisi adipisicing dolor dolor. Reprehenderit esse quis in consectetur do ipsum Lorem aliquip ullamco aliqua pariatur exercitation et reprehenderit.\r\n",
    "registered": "2023-08-08T03:14:19 +04:00",
    "latitude": -80.983118,
    "longitude": 10.057442,
    "tags": [
      "eu",
      "excepteur",
      "non",
      "et",
      "do",
      "in",
      "quis"
    ],
    "friends": [
      {
        "id": 0,
        "name": "Warren Castillo"
      },
      {
        "id": 1,
        "name": "Mueller Moses"
      },
      {
        "id": 2,
        "name": "Nikki Hunt"
      }
    ],
    "greeting": "Hello, Moss Alston! You have 4 unread messages.",
    "favoriteFruit": "strawberry"
  },
  {
    "_id": "6616cf978f04566816e4aead",
    "index": 1,
    "guid": "52fc0cb7-5295-46f6-8587-48ba9c9fbcfc",
    "isActive": false,
    "balance": "$3,693.44",
    "picture": "http://placehold.it/32x32",
    "age": 35,
    "eyeColor": "blue",
    "name": "Gomez Reese",
    "gender": "male",
    "company": "COMFIRM",
    "email": "gomezreese@comfirm.com",
    "phone": "+1 (921) 458-3418",
    "address": "467 Nichols Avenue, Keyport, Virgin Islands, 972",
    "about": "Cillum in cillum enim aute tempor culpa dolore adipisicing ullamco sunt enim. Eu amet esse duis occaecat. Aliquip exercitation aliqua mollit sit consequat.\r\n",
    "registered": "2018-06-16T08:17:14 +04:00",
    "latitude": 1.468837,
    "longitude": 67.744504,
    "tags": [
      "mollit",
      "quis",
      "in",
      "aute",
      "qui",
      "deserunt",
      "sit"
    ],
    "friends": [
      {
        "id": 0,
        "name": "Allyson Dejesus"
      },
      {
        "id": 1,
        "name": "Bean Parker"
      },
      {
        "id": 2,
        "name": "Shaffer Cox"
      }
    ],
    "greeting": "Hello, Gomez Reese! You have 3 unread messages.",
    "favoriteFruit": "strawberry"
  },
  {
    "_id": "6616cf97808c2062be947fb5",
    "index": 2,
    "guid": "37f18d2e-b57c-48aa-af17-43b1c8596782",
    "isActive": false,
    "balance": "$3,634.09",
    "picture": "http://placehold.it/32x32",
    "age": 30,
    "eyeColor": "brown",
    "name": "Dee Ross",
    "gender": "female",
    "company": "ONTALITY",
    "email": "deeross@ontality.com",
    "phone": "+1 (834) 466-3040",
    "address": "233 Church Avenue, Barronett, California, 1364",
    "about": "Labore enim aute Lorem consectetur ut enim aliquip proident irure minim velit ullamco. Id sunt exercitation ipsum sunt aliqua culpa cillum. Enim ipsum aute labore incididunt consectetur et occaecat ea enim minim. Et pariatur velit esse occaecat aliqua amet deserunt aute cillum.\r\n",
    "registered": "2016-03-03T11:14:58 +05:00",
    "latitude": -67.715968,
    "longitude": 49.444765,
    "tags": [
      "et",
      "aliqua",
      "pariatur",
      "mollit",
      "mollit",
      "enim",
      "sunt"
    ],
    "friends": [
      {
        "id": 0,
        "name": "Maynard Gilbert"
      },
      {
        "id": 1,
        "name": "Gillespie Kinney"
      },
      {
        "id": 2,
        "name": "Ebony Wooten"
      }
    ],
    "greeting": "Hello, Dee Ross! You have 6 unread messages.",
    "favoriteFruit": "banana"
  },
  {
    "_id": "6616cf9793ca876294c458e8",
    "index": 3,
    "guid": "385e0c85-9a5e-4c71-961f-2617a36d0216",
    "isActive": true,
    "balance": "$3,108.93",
    "picture": "http://placehold.it/32x32",
    "age": 23,
    "eyeColor": "blue",
    "name": "Mcbride Sanford",
    "gender": "male",
    "company": "MIRACLIS",
    "email": "mcbridesanford@miraclis.com",
    "phone": "+1 (825) 445-3236",
    "address": "417 Neptune Avenue, Blodgett, Tennessee, 430",
    "about": "Nulla cillum officia irure minim labore nulla non non nisi adipisicing. Nisi consequat exercitation dolor officia consectetur irure aliqua id ut incididunt. Magna ex velit tempor consectetur excepteur veniam non. Nisi ipsum aliqua consequat deserunt. Nisi aliqua ullamco ea irure fugiat adipisicing consectetur eiusmod occaecat magna ea elit occaecat. Anim do cillum dolor ullamco tempor magna adipisicing sit. Enim ut ex cillum nisi anim duis fugiat laboris dolor non.\r\n",
    "registered": "2017-03-14T10:09:52 +04:00",
    "latitude": -41.040594,
    "longitude": 118.570284,
    "tags": [
      "id",
      "proident",
      "voluptate",
      "Lorem",
      "nisi",
      "nostrud",
      "veniam"
    ],
    "friends": [
      {
        "id": 0,
        "name": "Hamilton Wilson"
      },
      {
        "id": 1,
        "name": "Jo Ramsey"
      },
      {
        "id": 2,
        "name": "Mariana Freeman"
      }
    ],
    "greeting": "Hello, Mcbride Sanford! You have 5 unread messages.",
    "favoriteFruit": "strawberry"
  },
  {
    "_id": "6616cf97209e12426dc7c436",
    "index": 4,
    "guid": "283a9582-5504-4573-a264-1b8cfae3c18a",
    "isActive": true,
    "balance": "$3,499.35",
    "picture": "http://placehold.it/32x32",
    "age": 34,
    "eyeColor": "brown",
    "name": "Whitehead Lynn",
    "gender": "male",
    "company": "WAZZU",
    "email": "whiteheadlynn@wazzu.com",
    "phone": "+1 (921) 526-3705",
    "address": "536 Kaufman Place, Allamuchy, New Jersey, 7803",
    "about": "Commodo ex aliqua veniam laboris. Eu labore nostrud cillum consequat quis excepteur pariatur magna sit culpa incididunt sunt enim esse. Voluptate occaecat in aliqua consequat mollit nostrud veniam eiusmod exercitation in excepteur nisi.\r\n",
    "registered": "2015-06-18T08:50:50 +04:00",
    "latitude": -25.162687,
    "longitude": -165.389453,
    "tags": [
      "laborum",
      "dolor",
      "id",
      "nostrud",
      "nostrud",
      "dolor",
      "mollit"
    ],
    "friends": [
      {
        "id": 0,
        "name": "Paulette Nieves"
      },
      {
        "id": 1,
        "name": "Hudson Mullins"
      },
      {
        "id": 2,
        "name": "Vicky Whitley"
      }
    ],
    "greeting": "Hello, Whitehead Lynn! You have 6 unread messages.",
    "favoriteFruit": "banana"
  },
  {
    "_id": "6616cf975eeed104be23ebd2",
    "index": 5,
    "guid": "eb10bf2e-05a1-4c19-8394-60e32bb74fa8",
    "isActive": true,
    "balance": "$2,293.90",
    "picture": "http://placehold.it/32x32",
    "age": 37,
    "eyeColor": "green",
    "name": "Kitty Chapman",
    "gender": "female",
    "company": "EVENTAGE",
    "email": "kittychapman@eventage.com",
    "phone": "+1 (879) 584-2576",
    "address": "422 Conselyea Street, Caroleen, Oklahoma, 8447",
    "about": "Cillum nostrud elit sint occaecat cupidatat officia nostrud adipisicing ea esse consequat excepteur. Do excepteur proident culpa nulla. Nostrud pariatur excepteur aliqua laborum labore velit veniam sunt sit.\r\n",
    "registered": "2020-03-24T08:39:54 +04:00",
    "latitude": 11.825471,
    "longitude": 130.754164,
    "tags": [
      "anim",
      "nulla",
      "fugiat",
      "eu",
      "aliqua",
      "non",
      "nulla"
    ],
    "friends": [
      {
        "id": 0,
        "name": "Britt Hebert"
      },
      {
        "id": 1,
        "name": "Marsh Brooks"
      },
      {
        "id": 2,
        "name": "Anastasia Gregory"
      }
    ],
    "greeting": "Hello, Kitty Chapman! You have 5 unread messages.",
    "favoriteFruit": "apple"
  }
]